{
  "Actor": {
    "types": [ "character", "minion_pack", "dungeon", "clock" ],
    "character": {
      "look": "",
      "vilefriend": "",
      "minionpack": "",
      "wickedxp": {
        "value": 0,
        "max": 9,
        "max_default": 9,
        "name_default": "FITD.WickedXP",
        "name": "FITD.WickedXP"
      },
      "recklessxp": {
        "value": 0,
        "max": 3,
        "max_default": 3,
        "name_default": "FITD.RecklessXP",
        "name": "FITD.RecklessXP"
      },
      "stress_clock": 0,
      "bloodied": false,
      "dark_hearts": 0,
      "gold": 0,
      "supply": 0,
      "max_supply": 2,
      "attribute_max_value": 3,
      "attributes": {
        "brains": {
          "shocked": false,
          "label": "FITD.SkillsBrains",
          "skills": {
            "scan": {
              "label": "FITD.SkillsScan",
              "value": 0,
              "practice": 0
            },
            "tinker": {
              "label": "FITD.SkillsTinker",
              "value": 0,
              "practice": 0
            },
            "trick": {
              "label": "FITD.SkillsTrick",
              "value": 0,
              "practice": 0
            }
          }
        },
        "muscles": {
          "shocked": false,
          "label": "FITD.SkillsMuscles",
          "skills": {
            "finesse": {
              "label": "FITD.SkillsFinesse",
              "value": 0 ,
              "practice": 0
            },
            "skulk": {
              "label": "FITD.SkillsSkulk",
              "value": 0,
              "practice": 0
            },
            "smash": {
              "label": "FITD.SkillsSmash",
              "value": 0,
              "practice": 0
            }
          }
        },
        "guts": {
          "shocked": false,
          "label": "FITD.SkillsGuts",
          "skills": {
            "banter": {
              "label": "FITD.SkillsBanter",
              "value": 0,
              "practice": 0
            },
            "invoke": {
              "label": "FITD.SkillsInvoke",
              "value": 0,
              "practice": 0
            },
            "threaten": {
              "label": "FITD.SkillsThreaten",
              "value": 0,
              "practice": 0
            }
          }
        }
      }
    },
    "minion_pack": {
      "bloodied": false,
      "morale": false,
      "number": 0,
      "attribute_max_value": 2,
      "attributes": {
        "brains": {
          "label": "FITD.SkillsBrains",
          "skills": {
            "scan": {
              "label": "FITD.SkillsScan",
              "value": [ 0 ]
            },
            "tinker": {
              "label": "FITD.SkillsTinker",
              "value": [ 0 ]
            },
            "trick": {
              "label": "FITD.SkillsTrick",
              "value": [ 0 ]
            }
          }
        },
        "muscles": {
          "label": "FITD.SkillsMuscles",
          "skills": {
            "finesse": {
              "label": "FITD.SkillsFinesse",
              "value": [ 0 ]
            },
            "skulk": {
              "label": "FITD.SkillsSkulk",
              "value": [ 0 ]
            },
            "smash": {
              "label": "FITD.SkillsSmash",
              "value": [ 0 ]
            }
          }
        },
        "guts": {
          "label": "FITD.SkillsGuts",
          "skills": {
            "banter": {
              "label": "FITD.SkillsBanter",
              "value": [ 0 ]
            },
            "invoke": {
              "label": "FITD.SkillsInvoke",
              "value": [ 0 ]
            },
            "threaten": {
              "label": "FITD.SkillsThreaten",
              "value": [ 0 ]
            }
          }
        }
      }
    },
    "dungeon": {
      "name": "",
      "tier": 0,
      "imps": "",
      "entrance": "",
      "structure": "",
      "lighting": "",
      "atmospherics": "",
      "hoard": "",
      "notes": "",
      "master_plan": {
        "step1": "",
        "step2": "",
        "step3": "",
        "step4": "",
        "step5": "",
        "step6": ""
      }
    }
  },
  "Item": {
    "types": [ "calling", "defense", "project", "duty", "dungeon_theme", "gear", "minionimpulse", "minion_type", "minion_upgrade", "monsterrace", "revelry", "specialability", "supply", "tier3room", "wickedimpulse" ],
    "templates": {
      "default": {
        "description": ""
      },
      "ability": {
        "description": "",
        "calling": "",
        "core": false
      },
      "logic": {
        "logic": ""
      },
      "minion_upgrade": {
        "description": "",
        "keyword": "",
        "use_checkbox": false,
        "checked": false
      }
    },
    "gear": {
      "templates": [ "default" ]
    },
    "supply": {
      "templates": [ "default" ]
    },
    "duty": {
      "templates": [ "default" ],
      "tier": 0,
      "type": ""
    },
    "project": {
      "templates": [ "default" ],
      "clock_sizes": [ 4, 6, 8 ],
      "clock_size": 4,
      "clock_progress": 0
    },
    "defense": {
      "description": "",
      "checked": false
    },
    "calling": {
      "templates": [ "default" ],
      "flashback_clues": ""
    },
    "specialability": {
      "templates": [ "ability", "logic" ]
    },
    "tier3room": {
      "templates": [ "default" ],
      "theme": "",
      "requirements": "",
      "missing_materials": false
    },
    "minion_upgrade": {
      "templates": [ "minion_upgrade" ]
    },
    "minion_job": {
      "templates": [ "default" ]
    },
    "monsterrace": {
      "templates": [ "default" ]
    },
    "wickedimpulse": {
      "templates": [ "default" ]
    },
    "minionimpulse": {
      "templates": [ "default" ]
    },
    "revelry": {
      "templates": [ "default" ]
    },
    "dungeon_theme": {
      "description": "",
      "special_name": "",
      "special_feature": ""
    }
  }
}
